genbq/__init__.py
genbq/__main__.py
genbq/example.py
genbq/loaders.py
genbq/py.typed
genbq-0.3.0.dist-info/entry_points.txt
genbq-0.3.0.dist-info/LICENSE
genbq-0.3.0.dist-info/WHEEL
genbq-0.3.0.dist-info/METADATA
genbq-0.3.0.dist-info/RECORD
